{
  "stocks": [
    {
      "symbol": "VUSA.L",
      "price": 93.79000091552734,
      "percent": -0.28174906647457665
    },
    {
      "symbol": "NVDA",
      "price": 178.10000610351562,
      "percent": 0.7637941179720651
    },
    {
      "symbol": "PLTR",
      "price": 150.07000732421875,
      "percent": 2.0398499518724122
    },
    {
      "symbol": "NVO",
      "price": 36.90999984741211,
      "percent": 0.5193449968058009
    },
    {
      "symbol": "SOFI",
      "price": 16.110000610351562,
      "percent": -0.739367773557843
    },
    {
      "symbol": "META",
      "price": 575.0499877929688,
      "percent": 0.3860052414341972
    },
    {
      "symbol": "AMZN",
      "price": 213.77000427246094,
      "percent": 0.55033126644447
    },
    {
      "symbol": "O",
      "price": 62.22999954223633,
      "percent": 0.6957921395409887
    },
    {
      "symbol": "ORCL",
      "price": 143.1699981689453,
      "percent": -1.3980728864012921
    }
  ],
  "crypto": [
    {
      "id": "ondo-finance",
      "price": 0.26891,
      "percent": 5.684645806923801
    },
    {
      "id": "avalanche-2",
      "price": 9.43,
      "percent": 8.81153848432975
    },
    {
      "id": "cardano",
      "price": 0.26157,
      "percent": 6.718480127693829
    }
  ],
  "last_updated": "08/04/2026 02:36"
}