{
  "stocks": [
    {
      "symbol": "VUSA.L",
      "price": 93.63749694824219,
      "percent": 0.5017696559885712
    },
    {
      "symbol": "NVDA",
      "price": 172.92999267578125,
      "percent": -1.1263621064715583
    },
    {
      "symbol": "PLTR",
      "price": 150.67999267578125,
      "percent": -0.8162238837669415
    },
    {
      "symbol": "NVO",
      "price": 36.529998779296875,
      "percent": -0.027370609477624926
    },
    {
      "symbol": "SOFI",
      "price": 16.899999618530273,
      "percent": -0.8797676332535322
    },
    {
      "symbol": "META",
      "price": 593.6599731445312,
      "percent": -0.7074924911720779
    },
    {
      "symbol": "AMZN",
      "price": 205.3699951171875,
      "percent": -0.8017706055079473
    },
    {
      "symbol": "O",
      "price": 60.95000076293945,
      "percent": -0.2454979329959874
    },
    {
      "symbol": "ORCL",
      "price": 149.67999267578125,
      "percent": -0.47872827408161944
    }
  ],
  "crypto": [
    {
      "id": "ondo-finance",
      "price": 0.254273,
      "percent": 2.015213931963129
    },
    {
      "id": "avalanche-2",
      "price": 9.45,
      "percent": 3.5358652675568534
    },
    {
      "id": "cardano",
      "price": 0.260094,
      "percent": 1.4433334106242057
    }
  ],
  "last_updated": "23/03/2026 13:12"
}